archive/blink.py
archive/fadeSAVE.py
examples/analog_in_with_neopxels.py
examples/analog_input.py
examples/analog_input2.py
examples/analog_input3.py
examples/blink.py
examples/dht.py
examples/digital_input_pullup.py
examples/doc_blink.py
examples/fade.py
examples/get_pico_pins.py
examples/hc_sr04.py
examples/hc_sr04_wifi.py
examples/i2c_adxl345_accelerometer.py
examples/i2c_adxl345_accelerometer2.py
examples/loop_back.py
examples/neopixels.py
examples/neopixels2.py
examples/neopixels3.py
examples/pwm_constant.py
examples/servo.py
examples/spi_mpu9250.py
examples/steppers_independent.py
examples/steppers_synchronized.py
examples/x.py
exp/argsx.py
exp/dict_com2.py
exp/dict_comp.py
exp/neopixel2.py
telemetrix_rpi_pico/__init__.py
telemetrix_rpi_pico/private_constants.py
telemetrix_rpi_pico/telemetrix_rpi_pico.py
venv/bin/activate_this.py
telemetrix_rpi_pico-1.5.1.dist-info/METADATA
telemetrix_rpi_pico-1.5.1.dist-info/WHEEL
telemetrix_rpi_pico-1.5.1.dist-info/top_level.txt
telemetrix_rpi_pico-1.5.1.dist-info/RECORD
